openapi_typed_2/__init__.py
openapi_typed_2/converters.py
openapi_typed_2/openapi.py
openapi_typed_2/py.typed
openapi_typed_2-0.0.5.dist-info/LICENSE
openapi_typed_2-0.0.5.dist-info/METADATA
openapi_typed_2-0.0.5.dist-info/WHEEL
openapi_typed_2-0.0.5.dist-info/top_level.txt
openapi_typed_2-0.0.5.dist-info/RECORD
